fairepay_api/__init__.py
fairepay_api/authorize.py
fairepay_api/customer/__init__.py
fairepay_api/customer/identity.py
fairepay_api/customer/orders.py
fairepay_api/customer/settings.py
fairepay_api/restaurant/__init__.py
fairepay_api/restaurant/orders.py
fairepay_api/restaurant/settings.py
fairepay_api/settings.py
fairepay_api-0.0.1.dist-info/METADATA
fairepay_api-0.0.1.dist-info/WHEEL
fairepay_api-0.0.1.dist-info/RECORD
